mbf_bam-0.6.0.dist-info/METADATA
mbf_bam-0.6.0.dist-info/WHEEL
mbf_bam/__init__.py
mbf_bam/mbf_bam.abi3.so
mbf_bam-0.6.0.dist-info/RECORD
