Metadata-Version: 2.3
Name: mbf_bam
Version: 0.6.0
Summary: Helpers to deal with BAM files
Keywords: bam,high troughput sequencing
Author: Florian Finkernagel <finkernagel@imt.uni-marburg.de>
Author-email: Florian Finkernagel <finkernagel@imt.uni-marburg.de>
License: MIT
Project-URL: Source Code, https://github.com/TyberiusPrime/mbf_bam
